{
    "currentPage": 16259,
    "pageSize": 20,
    "items": [
        {
            "id": "83ea12903aa144b6802e7283c245a0d6",
            "sentence": "Tom knows some words in French."
        },
        {
            "id": "4167b0d5706b4bf5a6e0a2c41d460883",
            "sentence": "Tom knows that Mary loves John."
        },
        {
            "id": "6b31b4407ee043c4a3c1401c6172e8da",
            "sentence": "Tom likes camping on the beach."
        },
        {
            "id": "1b2ca7d10fd047638c0326b8da5f1121",
            "sentence": "I have to think of my children."
        },
        {
            "id": "f90cb813ecf645e6bbe75023cf4c3f4e",
            "sentence": "I helped Tom clean the kitchen."
        },
        {
            "id": "1dc8db08db6a4d29bd5a1ad3c28cac97",
            "sentence": "I hope you brought an umbrella."
        },
        {
            "id": "fed6181869c843499be299f7d59af27e",
            "sentence": "How many more forks do we need?"
        },
        {
            "id": "692fc927752d4346810e10051f372f4b",
            "sentence": "How many more of you are there?"
        },
        {
            "id": "6d2e39853797436dab1569b2b75531c3",
            "sentence": "How many museums did you visit?"
        },
        {
            "id": "f64e2bf1cc8942f0a13114f8316a8783",
            "sentence": "How many people are here today?"
        },
        {
            "id": "0f7dbb574bd546509da964fbe1c6a699",
            "sentence": "How many pictures did Tom take?"
        },
        {
            "id": "693104eb40a048aba2b17e22fdc2aedf",
            "sentence": "How many sisters does Tom have?"
        },
        {
            "id": "64bb94e1d47e47e8bb5af29c4fd9315c",
            "sentence": "Tom wasn\\'t able to stay awake."
        },
        {
            "id": "723aa59506d6406588c729a64bbea140",
            "sentence": "Tom wasn\\'t able to work today."
        },
        {
            "id": "c26c29587ed54b7c95b82532ba0c5e74",
            "sentence": "Tom wasn\\'t allowed to do that."
        },
        {
            "id": "46397b0a75644cf3859e36fede99e05b",
            "sentence": "Tom wasn\\'t angry with anybody."
        },
        {
            "id": "35bb66089bcf40b8b3a745ce68fab879",
            "sentence": "Tom wasn\\'t as helpful as Mary."
        },
        {
            "id": "411c7bb641014b4a9e0a36cb68bee34d",
            "sentence": "Tom wasn\\'t at home last night."
        },
        {
            "id": "791527e7021d4e94bb0966f6a3212149",
            "sentence": "I could hardly believe my eyes."
        },
        {
            "id": "ee9edc17eb39418c97bee4d72a4dda0c",
            "sentence": "I don\\'t want to be distracted."
        }
    ],
    "nbPages": 35752,
    "nbResults": 715026
}