{
    "currentPage": 25045,
    "pageSize": 20,
    "items": [
        {
            "id": "2b59bbfa5f87449ab89d13b18a812a18",
            "sentence": "It rained almost every day last week."
        },
        {
            "id": "622bacd77c85493fa74f7e30675dad33",
            "sentence": "It wouldn't be wise to do that today."
        },
        {
            "id": "d6f5268f9b9d47bf8f1928634e10015d",
            "sentence": "Leave it to me. I'll take care of it."
        },
        {
            "id": "d1826257bd8a4c8889996dcfa5b3b21c",
            "sentence": "It wouldn't be a bad idea to do that."
        },
        {
            "id": "61cf30631986460d8f77c346977dff74",
            "sentence": "I don't plan to do that anytime soon."
        },
        {
            "id": "149b68b5161f4e4399c6741fd83f9332",
            "sentence": "I don't want to try doing that again."
        },
        {
            "id": "149fdddeee344c038cbadf0b0992e9ea",
            "sentence": "I don't want to go drinking with you."
        },
        {
            "id": "0367b8c5273444988a671a7842c9f8d7",
            "sentence": "I don't think you're being realistic."
        },
        {
            "id": "50ea0954738f4c7c9f1662ecc4d1595f",
            "sentence": "I don't think that's such a big deal."
        },
        {
            "id": "42d06986bf6e427c8d2bb94662c8116b",
            "sentence": "I don't think doing that would be OK."
        },
        {
            "id": "43fd3d975a6e44888d427f9b81ffb0c7",
            "sentence": "I don't think doing that is much fun."
        },
        {
            "id": "df0e4c198a074ba0ba81f9a6d70c07d4",
            "sentence": "I don't think I'm likely to be fired."
        },
        {
            "id": "8082fdd643b649bb9d59c1f5e712f001",
            "sentence": "I don't think I can buy that for you."
        },
        {
            "id": "865b1da589084975aaaef9eec0a1d064",
            "sentence": "I don't remember agreeing to do that."
        },
        {
            "id": "9cd9e67379db491a97eeda3926411042",
            "sentence": "I don't really need to do that today."
        },
        {
            "id": "3c3c9b0807714f2a8cb1029b9eb476aa",
            "sentence": "I don't really have to do that today."
        },
        {
            "id": "4f8f8b44df724ee08cd2d8b787bd852e",
            "sentence": "I don't often stay out late at night."
        },
        {
            "id": "84d543ec213041098777841f6af7d449",
            "sentence": "I don't like either of those options."
        },
        {
            "id": "302f7acce890437da93123e759c3ca9c",
            "sentence": "I don't care if my clothes get dirty."
        },
        {
            "id": "5b3523e83dca4ace9b4c0b97df0b14f3",
            "sentence": "I don't want you hanging around here."
        }
    ],
    "nbPages": 35752,
    "nbResults": 715026
}