{
    "currentPage": 29151,
    "pageSize": 20,
    "items": [
        {
            "id": "9814e86a52574d02bc192b75fe5db942",
            "sentence": "I think Tom and Mary have both done that."
        },
        {
            "id": "d2a9ffd877b5467dbc7332c5d075f8af",
            "sentence": "I know both Tom and Mary have to do that."
        },
        {
            "id": "366ed32c384c4b77b4fa1920ca07ce1b",
            "sentence": "I know Tom and Mary both have to do that."
        },
        {
            "id": "0eccc8279105411eb9b4c4f15d7ef8b8",
            "sentence": "Tom might know why Mary wants to do that."
        },
        {
            "id": "d0592f98ebeb489fb11449a829fe273f",
            "sentence": "I wonder whether or not we could do that."
        },
        {
            "id": "814e3197db704d7fbc5cf5eab74d46a4",
            "sentence": "I wonder whether we could do that or not."
        },
        {
            "id": "46414d848b5c48609fc0f0bd8e0803e2",
            "sentence": "I wonder whether Tom will do that or not."
        },
        {
            "id": "18324c412ae84b58a4a9bf2be543f205",
            "sentence": "Both Tom and Mary knew you could do that."
        },
        {
            "id": "06d49cbd1f494727ad17d4398df060c6",
            "sentence": "Tom and Mary both knew you could do that."
        },
        {
            "id": "31b4a33fb6344519b951767b38e248c0",
            "sentence": "Both Tom and Mary have agreed to do that."
        },
        {
            "id": "a8ea718fa9d44d0c9c24ef6083d93750",
            "sentence": "Tom and Mary have both agreed to do that."
        },
        {
            "id": "fa58e19da4d94b62a86d0d3b043e0509",
            "sentence": "Both Tom and Mary didn't want to do that."
        },
        {
            "id": "d0d702a79b654689b221145d0b325c32",
            "sentence": "Both Tom and Mary can do that quite well."
        },
        {
            "id": "b5b1db64ea41462e9e0d03b79306b5ab",
            "sentence": "Tom and Mary can both do that quite well."
        },
        {
            "id": "1b46e0a988734d55a01fe8038d9f2e46",
            "sentence": "Tom is only half way finished doing that."
        },
        {
            "id": "8da749d65de447a8a08c98663f35a4d7",
            "sentence": "Tom is getting pretty good at doing that."
        },
        {
            "id": "deaa9083efc24e6eba911fec5b47dba3",
            "sentence": "Tom asked if we'd done that by ourselves."
        },
        {
            "id": "f1cd95555e974e32b608056057a093be",
            "sentence": "Tom told me Mary wasn't ready to do that."
        },
        {
            "id": "790e3e72b1e242ff8ff52f9dd8304b4e",
            "sentence": "Tom told me Mary was prepared to do that."
        },
        {
            "id": "efca7a4780b447f39d4e8d49c9f04e0c",
            "sentence": "Tom told me Mary was hesitant to do that."
        }
    ],
    "nbPages": 35752,
    "nbResults": 715026
}