{
    "currentPage": 29367,
    "pageSize": 20,
    "items": [
        {
            "id": "8cb88064cd0b47f6ab27dee58576c83b",
            "sentence": "It looks like Tom is going to get married."
        },
        {
            "id": "92c63e7725fb41a4a99bd85d66462170",
            "sentence": "It looks like Tom is waiting for somebody."
        },
        {
            "id": "978fb354017e4a1a88cbd07d50ac47bf",
            "sentence": "When and where did you buy that old clock?"
        },
        {
            "id": "ce8dcb3e47404bc5876caae54650ea3d",
            "sentence": "Tom said that Mary has been sick all week."
        },
        {
            "id": "b1449cbc200e4d33af3f3cb9939933ac",
            "sentence": "Tom said that Mary looked really confused."
        },
        {
            "id": "9c24058ce1e94f30b62593299af8e86c",
            "sentence": "Tom said that Mary might return on Monday."
        },
        {
            "id": "797742e03060405d8697d010a98ee274",
            "sentence": "Tom said that Mary needed to be protected."
        },
        {
            "id": "d44c08f4745949829e314b4c5f1835a7",
            "sentence": "It\\'s a quarter after nine in the morning."
        },
        {
            "id": "097a82a9274244ddb332c311c5b3fa32",
            "sentence": "Where do you think I should go to college?"
        },
        {
            "id": "88b710442eb441929c3cf99486fc6177",
            "sentence": "Where do you want me to put this suitcase?"
        },
        {
            "id": "67ed2e1d6bbd4dacabb51844b6007b9e",
            "sentence": "Tom and Mary are waiting in the next room."
        },
        {
            "id": "896ad22ad1064def80ffc6dbb3bba247",
            "sentence": "I\\'ve been looking forward to meeting you."
        },
        {
            "id": "e9b4922ad3184b62a03f3574b1dc21e6",
            "sentence": "I didn\\'t know your mother lived with you."
        },
        {
            "id": "d357ab9f15d947aa9933870303ae0f1d",
            "sentence": "I didn\\'t like being kept waiting so long."
        },
        {
            "id": "1975b9541a174dedabf2ac5d58b8eee4",
            "sentence": "I didn\\'t tell Tom I grew up in Australia."
        },
        {
            "id": "54b61a593cbc40c6bb75befb749f969c",
            "sentence": "Both of my parents were born in Australia."
        },
        {
            "id": "58dba156832a47d3bcf53ecc2e41d87a",
            "sentence": "Can I have your name and telephone number?"
        },
        {
            "id": "980ee0adccdb45048c3b4d719181f8a3",
            "sentence": "Can you let me have it for thirty dollars?"
        },
        {
            "id": "cd1b705333e14e3fb4cbf94ce563dba8",
            "sentence": "Tell Tom how he can get in touch with you."
        },
        {
            "id": "ed390b06cfbe4a8b98fdb67e0a8b9c8f",
            "sentence": "Tell me who you plan to go to Boston with."
        }
    ],
    "nbPages": 35752,
    "nbResults": 715026
}