{
    "currentPage": 30398,
    "pageSize": 20,
    "items": [
        {
            "id": "d5c0893a05774ee1a51c10f7c448ac0e",
            "sentence": "How can you be sure that's going to happen?"
        },
        {
            "id": "9d1afb01933f4a5cb7634f79b708c2e3",
            "sentence": "Tom was supposed to help me, but he didn't."
        },
        {
            "id": "4c8ad45b228d412f951d8ec4b7990705",
            "sentence": "I wouldn't be able to do that for a living."
        },
        {
            "id": "c7580be61f334380941733a7760b70db",
            "sentence": "Don't tell me that you've lost your ticket."
        },
        {
            "id": "02524c73ee34455fb9b64386f06cfadd",
            "sentence": "Tom was stopped at the border and searched."
        },
        {
            "id": "11c08ae98da740cf87534fb04de4447c",
            "sentence": "This restaurant is only open in the summer."
        },
        {
            "id": "b9bbf6cb73d14e32b24e7236d1c77ba4",
            "sentence": "That isn't the kind of thing we like to do."
        },
        {
            "id": "dc07dffc375b4fc7b72944dfaef94185",
            "sentence": "Tom has to stay even if he doesn't want to."
        },
        {
            "id": "664d15bc90eb4d39b9d2e1b62aaddc35",
            "sentence": "I drove to Boston in less than three hours."
        },
        {
            "id": "9c58f23ef68a4339b77f66600c2daca7",
            "sentence": "I may not be able to handle this situation."
        },
        {
            "id": "f8340ad2d14b482a9e6b0dbbca6b6b5f",
            "sentence": "Tom is actually a pretty good chess player."
        },
        {
            "id": "55cf2593e25a44e7addadfc46c8bd08f",
            "sentence": "There are so many places I'd like to visit."
        },
        {
            "id": "629a2a005a41472db639fa9eb2e2ae2c",
            "sentence": "Tom and Mary stayed in their rooms all day."
        },
        {
            "id": "63870522e90846a6874b3c781804782a",
            "sentence": "Tom paid Mary to take care of his children."
        },
        {
            "id": "66157553e5164f0cbeb32a7daa2cd3c5",
            "sentence": "We're not exactly sure what the problem is."
        },
        {
            "id": "6ad8cbcf8c114d90b0437caaec2d3657",
            "sentence": "Tom made me so angry that I hung up on him."
        },
        {
            "id": "d8d4fe2084884a0dac3c69e33d0f5e40",
            "sentence": "Tom liked almost everything about the trip."
        },
        {
            "id": "0da34ac8021e4f44865710110d922a1a",
            "sentence": "How long does it take you to take a shower?"
        },
        {
            "id": "4fa91cd7a5c2415ca000aadc861a22bd",
            "sentence": "Why aren't you wearing your safety goggles?"
        },
        {
            "id": "eaa171b87c4c4c0e855d15a917152b9e",
            "sentence": "Do you think I should allow Tom to do that?"
        }
    ],
    "nbPages": 35752,
    "nbResults": 715026
}