{
    "currentPage": 4007,
    "pageSize": 20,
    "items": [
        {
            "id": "41e6418549b64ab49c522162ccde68b1",
            "sentence": "Tom will be executed."
        },
        {
            "id": "eacb67bddc8149aca7fa333c532fc5e4",
            "sentence": "Tom will be so sorry."
        },
        {
            "id": "e569fcd26eda48c0941ac7f9ba87cf1e",
            "sentence": "Tom will do it again."
        },
        {
            "id": "9ee972b655f94a6cb88b64a897a66af4",
            "sentence": "Tom will do the same."
        },
        {
            "id": "acd33bf30da14f9e97609216e8710d67",
            "sentence": "Tom will go see Mary."
        },
        {
            "id": "6c8e97f02dd54daf83070609b7c4bd7b",
            "sentence": "Why don\\'t we all go?"
        },
        {
            "id": "22f4e30fefd44fe2bcf4a616c7c7242c",
            "sentence": "Why don\\'t we go out?"
        },
        {
            "id": "e531cb14c82e448c9a93e46b195bfc7b",
            "sentence": "Why don\\'t you do it?"
        },
        {
            "id": "b2cce7bccac9415e8064b432206d3f8a",
            "sentence": "Why don\\'t you enter?"
        },
        {
            "id": "3c5fcc4c35a04afcb61b4a6c2c7c377c",
            "sentence": "Why don\\'t you guess?"
        },
        {
            "id": "a9ec00583df24773a466b6788783f458",
            "sentence": "Nobody else got hurt."
        },
        {
            "id": "85db9a177dd4404b860bfb1c9d34da84",
            "sentence": "Can I throw this out?"
        },
        {
            "id": "5c68a8a5dbc6449d8d1199107082e45c",
            "sentence": "Can I walk down here?"
        },
        {
            "id": "beea596511c24b8fba28f179476158d5",
            "sentence": "I\\'m really not busy."
        },
        {
            "id": "3369bca1a6e24b99bc6375b4353df2b7",
            "sentence": "I\\'m terribly hungry."
        },
        {
            "id": "21ce5241115e49f89483e98f3d16ecd2",
            "sentence": "No one reads my blog."
        },
        {
            "id": "e7b08a6793ae403682769ce8f5127d38",
            "sentence": "No one recognized me."
        },
        {
            "id": "366d7f05ed244bc9a6d8a345a30f3c15",
            "sentence": "No one saw Tom leave."
        },
        {
            "id": "f0900bf362c344498c2d998f4cb257bd",
            "sentence": "Tom is the real hero."
        },
        {
            "id": "6ed15da12ee149cfbc15ce235373de4d",
            "sentence": "One of them is a spy."
        }
    ],
    "nbPages": 35752,
    "nbResults": 715026
}