{
    "currentPage": 12329,
    "pageSize": 50,
    "items": [
        {
            "id": "7201f62d5f2644c4891a54374e43b30f",
            "sentence": "I suspect Tom and Mary have lived in Boston."
        },
        {
            "id": "2a210ec13ae64bc1b1b35bf3336fd8d3",
            "sentence": "I suspect Tom and Mary have to go to Boston."
        },
        {
            "id": "fd8751eb3c5a484cabe0804949daa48a",
            "sentence": "I suspect Tom and Mary want us to help them."
        },
        {
            "id": "90f1dbe2705c45c4ae42105181a423a9",
            "sentence": "Tom admitted he didn\\'t like Mary very much."
        },
        {
            "id": "83e817ffe2484686a1c237d64f83dcbf",
            "sentence": "What\\'s the weirdest dream you\\'ve ever had?"
        },
        {
            "id": "c9d36cbfda6f4c5b944b033788d756ad",
            "sentence": "Tom is only pretending he isn\\'t interested."
        },
        {
            "id": "df712eecb1ec456bb3fedaecbc247f7a",
            "sentence": "Do you have your driver\\'s license with you?"
        },
        {
            "id": "9e7df53bbd2d471ca126f5bc4eac537c",
            "sentence": "I can\\'t help wondering if Tom will do that."
        },
        {
            "id": "e450c286087a4640b1e94a91b23c4e63",
            "sentence": "Tom said it could take a few hours to do it."
        },
        {
            "id": "2bb0df3808d1465580372d238efe3e0b",
            "sentence": "Do yourself a favor and get out of here now."
        },
        {
            "id": "19b757df91b5477d9a96837a1d92841c",
            "sentence": "Tom tried to get Mary to pay for his ticket."
        },
        {
            "id": "c80e1af5d7a14272ab6060c2a6b88a46",
            "sentence": "Tom lay awake for hours thinking about Mary."
        },
        {
            "id": "99610625ed5c4fc68d329aceb6dc11e5",
            "sentence": "Tom lay awake in bed, listening to the rain."
        },
        {
            "id": "343d90254236464a905f4011526a0b4f",
            "sentence": "Tom leaned across the table and kissed Mary."
        },
        {
            "id": "93ede15bd93143c1a3f9c3b7a4b46979",
            "sentence": "Tom leaned in close so he could hear better."
        },
        {
            "id": "b1d0be7c867f4b8bada316bb39c0cfe3",
            "sentence": "Tom can be really funny when he wants to be."
        },
        {
            "id": "569f8efcf9544ee283314ce59ad0c7b0",
            "sentence": "Tom knew Mary was going to be in the office."
        },
        {
            "id": "25c133ed172a4930b5b716b33a978380",
            "sentence": "Tom should just tell Mary he made a mistake."
        },
        {
            "id": "6d3d410bbd5948ea85874174ec733bb6",
            "sentence": "Tom should never have gone there by himself."
        },
        {
            "id": "47cde60bf5394d798d0e1841e3d430df",
            "sentence": "I\\'m not very interested in learning French."
        },
        {
            "id": "c8453f2a28bd43bd8b98485cc03d43bf",
            "sentence": "How many times has Tom done that by himself?"
        },
        {
            "id": "44c8120b87a14e8887a2354fb66062d5",
            "sentence": "I\\'m sick and tired of all your complaining."
        },
        {
            "id": "3cd6b0e9c27346269aefba4d38c4b73d",
            "sentence": "I\\'m sick of doing the same thing every day."
        },
        {
            "id": "52f83f8c4de84142bb28797081cdf0dc",
            "sentence": "Have you ever mentioned this to the teacher?"
        },
        {
            "id": "76471f151c814423b2ebdf348830e513",
            "sentence": "Have you put up your Christmas tree already?"
        },
        {
            "id": "d315ed0b815047a390b004303f41f4b6",
            "sentence": "Tom wasn\\'t as hungry as I thought he\\'d be."
        },
        {
            "id": "cdc7dd4e91364e2d8f3d177c67ef3b74",
            "sentence": "Tom told me he\\'d be at tomorrow\\'s meeting."
        },
        {
            "id": "40945871cb8d452f9c6f7cea0f06e2b2",
            "sentence": "Everyone knows that Tom has a thing for you."
        },
        {
            "id": "46321eeb32ba408e83a4c6764f9eb6bd",
            "sentence": "How long have you been living in this house?"
        },
        {
            "id": "57f53899d3304fbfa537127fe55ce90e",
            "sentence": "How much chocolate did you eat last weekend?"
        },
        {
            "id": "a871b2c281b64628b865361465a340de",
            "sentence": "What made you think that Tom wouldn\\'t come?"
        },
        {
            "id": "9959afbd10534397a6bd5a2bb67914c0",
            "sentence": "I finished cleaning my room a half hour ago."
        },
        {
            "id": "740f06f900bb4403ba088f558361a3bb",
            "sentence": "I need your advice on what I should do next."
        },
        {
            "id": "99e30d43811c4f948abc2c0420e05598",
            "sentence": "How was I to know Tom would change his mind?"
        },
        {
            "id": "87306325c4424c318e297feef034a0e3",
            "sentence": "I advised Tom not to go to Boston with Mary."
        },
        {
            "id": "986de0d163df447384480e4ae15464d5",
            "sentence": "I had a raincoat on so I didn\\'t get so wet."
        },
        {
            "id": "7b797a13add548f4905b428388a1df2d",
            "sentence": "You\\'ve thought of everything, haven\\'t you?"
        },
        {
            "id": "1e42eb5fcbc9436badd36e67fa966676",
            "sentence": "We weren\\'t invited to the opening ceremony."
        },
        {
            "id": "6229abc6605c404291157e7353e764d7",
            "sentence": "We\\'ll try to get there as soon as possible."
        },
        {
            "id": "6606cdc0145e43188ed66a56cfc932c9",
            "sentence": "What do you think happened to your suitcase?"
        },
        {
            "id": "e51d43f270534d6ba3afc26a04b1af59",
            "sentence": "Why do you think Tom likes baseball so much?"
        },
        {
            "id": "9028d532afa54a3b851bdaf4a27f0305",
            "sentence": "Tom told me he didn\\'t want to go to Boston."
        },
        {
            "id": "96b4c344cbf14daea18cd66f67a4f369",
            "sentence": "Tom told me he thought he couldn\\'t do that."
        },
        {
            "id": "36ce97078e3f419db7d0eb41441c40c1",
            "sentence": "Tom and Mary were pinned under the wreckage."
        },
        {
            "id": "dee177bff9764dbd8a0f7e9ade73f9ac",
            "sentence": "Tom and Mary were talking about the weather."
        },
        {
            "id": "5fae97cac5334783bea2a2f0aa1afc0d",
            "sentence": "Tom announced that he was quitting football."
        },
        {
            "id": "f53275a6bfeb4d3c8713601f15da8c45",
            "sentence": "Tom anticipated that there would be trouble."
        },
        {
            "id": "a3a5cdd60e52458fa6d54a9293b689b0",
            "sentence": "Tom apologized for calling so late at night."
        },
        {
            "id": "0b895f9a85344a09949979ecdad66dc9",
            "sentence": "I can\\'t forgive Tom for behaving like that."
        },
        {
            "id": "ca57b6aa8afe425598134d22ff9ce535",
            "sentence": "I can\\'t go to the concert with you tonight."
        }
    ],
    "nbPages": 14301,
    "nbResults": 715026
}