{
    "currentPage": 1697,
    "pageSize": 50,
    "items": [
        {
            "id": "346f25fa8e0d424ab1e12243007c1a83",
            "sentence": "Tom initially agreed."
        },
        {
            "id": "51a6b409ca5c462b953d2721a02d8b70",
            "sentence": "Tom inserted the key."
        },
        {
            "id": "3a62aa32f7e041fcbfa705e3936eb291",
            "sentence": "Tom knows the stakes."
        },
        {
            "id": "7ad4b19a341544ba9915e58ed8bfe089",
            "sentence": "Tom knows this place."
        },
        {
            "id": "a0de95b277864c28a3d330bfd88d6786",
            "sentence": "I almost didn\\'t win."
        },
        {
            "id": "f7a56f81ec7d48fd93c446bcf44a40cf",
            "sentence": "We\\'ll talk with Tom."
        },
        {
            "id": "c9e476d2f8ee405aa026dd33c268e91c",
            "sentence": "We\\'ll vouch for Tom."
        },
        {
            "id": "2237d11c86244ae490afffc3fcf2e730",
            "sentence": "They drank smoothies."
        },
        {
            "id": "29235a0741294c77b253e309aedc2d0d",
            "sentence": "Tom fell in the pool."
        },
        {
            "id": "946aa402a080449dbaa1ab31939b3493",
            "sentence": "I really miss my mom."
        },
        {
            "id": "5f589abb17584db9abe3d9de7c3cf684",
            "sentence": "What day is it again?"
        },
        {
            "id": "56ed5dde8e234b9683a98019746f4488",
            "sentence": "I love these gadgets."
        },
        {
            "id": "7b6f429227db4492b2e1e87ba07fd527",
            "sentence": "Didn\\'t you tell Tom?"
        },
        {
            "id": "7064570da9ac4eb28400c841f6a74d0c",
            "sentence": "Everyone has a price."
        },
        {
            "id": "298127ff5c7e4008b73ed37ebf10aab8",
            "sentence": "I have so much to do."
        },
        {
            "id": "4808e6917b8940799f40dff80ce2cbc3",
            "sentence": "Do you have ashtrays?"
        },
        {
            "id": "d8d3ebd0559649e3948551230366efba",
            "sentence": "I just went shopping."
        },
        {
            "id": "743fba7dabed4d47b812347d1adc0643",
            "sentence": "I kicked the door in."
        },
        {
            "id": "a5ee06433b534408855f66636ea2ff4f",
            "sentence": "I think no one knows."
        },
        {
            "id": "32e14529fd5e4d6a95cce9adc937a17e",
            "sentence": "I thought I was dead."
        },
        {
            "id": "f1a393682b2d4e76bf57a8d1bff40631",
            "sentence": "I thought Tom did it."
        },
        {
            "id": "bedddc04620343389e2adcaeabddfff3",
            "sentence": "I told Tom the story."
        },
        {
            "id": "63ef3e2d003c428faee8fe4008199afa",
            "sentence": "I bought some apples."
        },
        {
            "id": "12577b7e22d84daf95e54a6b3bf78181",
            "sentence": "I bought three books."
        },
        {
            "id": "77d5b970f90242488778abc4957078fa",
            "sentence": "This is a small town."
        },
        {
            "id": "30a342e1963e46e1a3a8be20b004bc37",
            "sentence": "Tom started mumbling."
        },
        {
            "id": "090fcdfa17b840d38c29b171689ee8bf",
            "sentence": "What makes it unique?"
        },
        {
            "id": "8b434e5db89c4c8b8080757906410e60",
            "sentence": "Let\\'s not ruin this."
        },
        {
            "id": "0b9ce654ab024507b63a3e0562a7187f",
            "sentence": "I wasn\\'t having fun."
        },
        {
            "id": "8c72b3c84411468c8be657f2915a3751",
            "sentence": "I wasn\\'t indiscreet."
        },
        {
            "id": "58cf3c08f3be404da293c083a501f19b",
            "sentence": "I shouldn\\'t do this."
        },
        {
            "id": "572608edab82492b800f84a5e3bd6418",
            "sentence": "I simply don\\'t know."
        },
        {
            "id": "be3a5d82226640108171a7515006f6c4",
            "sentence": "I won\\'t talk to you."
        },
        {
            "id": "d9f27ab6ff9f461894c490054328bbb5",
            "sentence": "I won\\'t let you pay."
        },
        {
            "id": "e8e788f735434ce89b82ec5242512472",
            "sentence": "I won\\'t make you go."
        },
        {
            "id": "dc17eb01e097482cad09c7816b273b24",
            "sentence": "I won\\'t pay for you."
        },
        {
            "id": "0aab75a9cda54e20966c78237435ba25",
            "sentence": "I got angry with Tom."
        },
        {
            "id": "484a8261729d4d75add762d8a6a32f19",
            "sentence": "I got back in my car."
        },
        {
            "id": "8d3d44ee7f1449bd89e8efccc1a582b7",
            "sentence": "I got drunk with Tom."
        },
        {
            "id": "76e10dc31ae0423daba915f782bb2b07",
            "sentence": "Did I arrive on time?"
        },
        {
            "id": "3bde6a3daa0d43e387a0b1546cbccc60",
            "sentence": "I wanted to find Tom."
        },
        {
            "id": "cef4bd7a8c64478dbdf54ab1cb970a3a",
            "sentence": "We\\'ve got something."
        },
        {
            "id": "f6a57bacc80e4e138a968ced5a8a8f32",
            "sentence": "We\\'ve prepared well."
        },
        {
            "id": "8e4df752b0aa4e39ad6a6d11bf28c1b7",
            "sentence": "Tom is very diligent."
        },
        {
            "id": "592c08beef9e4064ab1a25077d9be8c6",
            "sentence": "That did happen once."
        },
        {
            "id": "11f59c6a1a074db59c19816b269d7d71",
            "sentence": "There are no threats."
        },
        {
            "id": "00e259de9e334430bbe1f4f9ba28e9eb",
            "sentence": "There can be dangers."
        },
        {
            "id": "252bfc7b85fb4a4c8f2dad851317f74d",
            "sentence": "Your parents hate me."
        },
        {
            "id": "7c2832465d514e17a6c4ed395ed3d917",
            "sentence": "Your phone just rang."
        },
        {
            "id": "2df2a8a491794458bc663378f34c53ac",
            "sentence": "We\\'ll talk this out."
        }
    ],
    "nbPages": 14301,
    "nbResults": 715026
}