{
    "currentPage": 108778,
    "pageSize": 5,
    "items": [
        {
            "id": "da806d42320b440297563594e8e50112",
            "sentence": "How did you know I needed one of these?"
        },
        {
            "id": "976430e11d6d46d99e599f227936cc38",
            "sentence": "How did you know I wanted one of these?"
        },
        {
            "id": "4b79f2bf942a4e07a0e5aa3ab20f2e92",
            "sentence": "How do things like this keep happening?"
        },
        {
            "id": "dc76577351294d13a7b4522f64a5124d",
            "sentence": "How do you choose which projects to do?"
        },
        {
            "id": "884f9e78ace9411eaa7e5898e0d28048",
            "sentence": "How do you decide what's right for you?"
        }
    ],
    "nbPages": 143006,
    "nbResults": 715026
}