{
    "currentPage": 131435,
    "pageSize": 5,
    "items": [
        {
            "id": "f71d9016c3a74994a2346493019f2af7",
            "sentence": "I had scarcely walked a minute before I met Tom."
        },
        {
            "id": "4cbfaaa067404dd79e976bb34b7d07bf",
            "sentence": "A lot of red flowers are blooming in the garden."
        },
        {
            "id": "189b899ed83a45c0b24e7e64ca1863a5",
            "sentence": "The Beatles gave five concerts in Tokyo in 1996."
        },
        {
            "id": "a653432846d44669b6aa410eb1cffdc4",
            "sentence": "Because of my job, I will be in Tokyo next week."
        },
        {
            "id": "9ed0a9915c12481ca7527eabc8059ffb",
            "sentence": "From time to time, he goes to Tokyo on business."
        }
    ],
    "nbPages": 143006,
    "nbResults": 715026
}