{
    "currentPage": 21610,
    "pageSize": 5,
    "items": [
        {
            "id": "b5332b6e0e8f436592b7743e56b9dca4",
            "sentence": "Privacy doesn't exist."
        },
        {
            "id": "090502b918154f94afb904eb38ba8120",
            "sentence": "The news troubled Tom."
        },
        {
            "id": "93382d5cda7844cc8dbdfb6ea5497e11",
            "sentence": "Tom started panicking."
        },
        {
            "id": "8125b58f64824029ab9b56e01ef934b2",
            "sentence": "Tom started to hit me."
        },
        {
            "id": "93e30b6b0d7f4fd1991fd9a40c377ae2",
            "sentence": "I don't eat ice cream."
        }
    ],
    "nbPages": 143006,
    "nbResults": 715026
}