{
    "currentPage": 26099,
    "pageSize": 5,
    "items": [
        {
            "id": "8a4f7220f042496683b2177d78b2fa12",
            "sentence": "I could've been a star."
        },
        {
            "id": "0a69adb3587b486a9afdc1388888bed8",
            "sentence": "I began to feel uneasy."
        },
        {
            "id": "3595b0aff5c2409ba5d2f37499d253e1",
            "sentence": "Tom walked to the mall."
        },
        {
            "id": "2b59149e4ed6421fba669bb4d13c0555",
            "sentence": "Tom didn't walk inside."
        },
        {
            "id": "e59f2647a26a49589d6e547197fc24cc",
            "sentence": "Tom was my first crush."
        }
    ],
    "nbPages": 143006,
    "nbResults": 715026
}