{
    "currentPage": 2708,
    "pageSize": 5,
    "items": [
        {
            "id": "0f03bc10d2a042549bbabdcb41a8b174",
            "sentence": "I like mustard."
        },
        {
            "id": "bd07432c30d24601b7ad0b1841071d10",
            "sentence": "My heart aches."
        },
        {
            "id": "aa8d551b6796499db28506af28d009ae",
            "sentence": "I kept the dog."
        },
        {
            "id": "0aa6d908bd95494d9454f0c20104e49b",
            "sentence": "I learn French."
        },
        {
            "id": "eb27024baa114484b7fd641dafa8aedd",
            "sentence": "Tom stayed put."
        }
    ],
    "nbPages": 143006,
    "nbResults": 715026
}