{
    "currentPage": 28931,
    "pageSize": 5,
    "items": [
        {
            "id": "62d8b545f733444ba04f021309f65b71",
            "sentence": "Tom is a bad role model."
        },
        {
            "id": "8cd6c057757949e4a99c0b624bcc7378",
            "sentence": "We should eat something."
        },
        {
            "id": "bc4e5500750c4a2fa665ab22d6ce138d",
            "sentence": "I\\'m Tom\\'s stepbrother."
        },
        {
            "id": "8d853bc08e9f406bbbfbebe5ecad3d36",
            "sentence": "This is not a good sign."
        },
        {
            "id": "a9395649deba4416869097b226071efe",
            "sentence": "This is not about money."
        }
    ],
    "nbPages": 143006,
    "nbResults": 715026
}