{
    "currentPage": 41285,
    "pageSize": 5,
    "items": [
        {
            "id": "344fa589f98248f5afd95f1a67593e07",
            "sentence": "Tom has been laid to rest."
        },
        {
            "id": "a8732ad7488b4cb49aacbe0e783d1024",
            "sentence": "Tom came to check on Mary."
        },
        {
            "id": "e0842f7b9c92486491f48380f56bdfee",
            "sentence": "Tom could make Mary laugh."
        },
        {
            "id": "9d3c1f524ed34a90a3b165dda91264ba",
            "sentence": "Tom could've been annoyed."
        },
        {
            "id": "cf58dcfc06b3424f9500b40cd4b9d957",
            "sentence": "Tom could've been jealous."
        }
    ],
    "nbPages": 143006,
    "nbResults": 715026
}