{
    "currentPage": 91453,
    "pageSize": 5,
    "items": [
        {
            "id": "aec1777525ac4407a6369ddefd6b541b",
            "sentence": "Does Tom have to be doing that now?"
        },
        {
            "id": "a13159b7a9fc4476954a04bf5e8a27a3",
            "sentence": "Does Tom have the skill to do that?"
        },
        {
            "id": "c985c19cbbc945d4877b9fd04a15aa69",
            "sentence": "Do you think Tom is doing that now?"
        },
        {
            "id": "c685db92086a4ec5b9114129784b503e",
            "sentence": "Do you still permit Tom to do that?"
        },
        {
            "id": "1ba4af3b929044a28218cc29c02f3fd5",
            "sentence": "Do you know why Tom had to do that?"
        }
    ],
    "nbPages": 143006,
    "nbResults": 715026
}