{
    "currentPage": 1634,
    "pageSize": 200,
    "items": [
        {
            "id": "974d427039f64d84a1ab3d9486a3478e",
            "sentence": "I was late for the appointment."
        },
        {
            "id": "feb544d5ccc548c8bcf8f40f2e6b327f",
            "sentence": "Is it true that Tom kissed you?"
        },
        {
            "id": "dd1bcc9ffd8246019b7e8c0f26e20334",
            "sentence": "Is it true that you kissed Tom?"
        },
        {
            "id": "111c504d350542c49cc42a9e2ecce7d9",
            "sentence": "It was Tom who found your keys."
        },
        {
            "id": "897d1971c8454894ada3893f9fea1db7",
            "sentence": "I can almost touch the ceiling."
        },
        {
            "id": "879e5624692a47859470c82cb94fa724",
            "sentence": "I can do that and Tom can, too."
        },
        {
            "id": "3f070ea7f34f4f5e981771c86362c2e3",
            "sentence": "I can do that without any help."
        },
        {
            "id": "5964548194014229a48b5dc6eaae6b86",
            "sentence": "I can get you something to eat."
        },
        {
            "id": "2df0332a99e14698839a664e4256a760",
            "sentence": "I can hardly believe his story."
        },
        {
            "id": "d1dbd268ab6d4d7badd77d40104a540e",
            "sentence": "I want you to wait for me here."
        },
        {
            "id": "528ea8014f2d45afac644e7a2367b995",
            "sentence": "I wanted Tom to clean his room."
        },
        {
            "id": "b7633f1593094c48bdb33dd430cb0f3e",
            "sentence": "There\\'s a cat under the table."
        },
        {
            "id": "7c8a38446d0645dabdddfe69d17c6039",
            "sentence": "There\\'s a magazine in my room."
        },
        {
            "id": "1a1f3bccd8134e408bbaac909edcca0d",
            "sentence": "There\\'s got to be another way."
        },
        {
            "id": "6af1f1f5b3314f3491191ec97322f174",
            "sentence": "There\\'s hardly any wind today."
        },
        {
            "id": "25360934d0704c12bda7343a915a9099",
            "sentence": "Do you have this in black, too?"
        },
        {
            "id": "4a94207976e94c0d8d1cf9b658922141",
            "sentence": "Do you have to work on Sundays?"
        },
        {
            "id": "08541140d91a4754a81a925c2b4625c6",
            "sentence": "Do you have your iPad with you?"
        },
        {
            "id": "91c88c7635c14ec8a85fc1bc3deddf1f",
            "sentence": "Do you have your own apartment?"
        },
        {
            "id": "3adf04e1afbb45ee9e00083de0c7d558",
            "sentence": "What\\'re Tom and Mary planning?"
        },
        {
            "id": "d5e13cba63e04ca9adc8d07471d39ca4",
            "sentence": "What\\'s Tom going to tell Mary?"
        },
        {
            "id": "8571c6f069b9445484af7709fa56e489",
            "sentence": "Tom went to see Mary in Boston."
        },
        {
            "id": "319c4ab57fb24444a12b6c1776cf5874",
            "sentence": "Tom went up to the third floor."
        },
        {
            "id": "5e9d3589487d44999dd7c001d5ded4fc",
            "sentence": "Tom whipped out his smartphone."
        },
        {
            "id": "9f5d53f1f4a847a0b29b1049807d6f8c",
            "sentence": "Tom will arrive within an hour."
        },
        {
            "id": "3feea11e6f3b4aa89dfde5b2e40bc6b3",
            "sentence": "I just figured out who you are."
        },
        {
            "id": "e04e13c0c4584ee8b9b1061ae439fe6a",
            "sentence": "When does the last train leave?"
        },
        {
            "id": "2c676635f11944a180cee7c05bde784f",
            "sentence": "When does the rainy season end?"
        },
        {
            "id": "70472a5818f7458e9e4e781fe12cd310",
            "sentence": "When was the last time you ate?"
        },
        {
            "id": "578e0dcf634c4b5f9747e8349c8788d0",
            "sentence": "When will the party take place?"
        },
        {
            "id": "8ac945a21e7e49e8b34b19ebb4dc124a",
            "sentence": "This has got to mean something."
        },
        {
            "id": "7fb5d7a9f3bb468892f53850247f75ee",
            "sentence": "I\\'d really rather go swimming."
        },
        {
            "id": "226dc33abea64dc6b7f7b861654b13c3",
            "sentence": "I\\'d really rather not do that."
        },
        {
            "id": "7ee7d4959136420591f11500e3efdbbf",
            "sentence": "I\\'d say Tom is pushing thirty."
        },
        {
            "id": "c7f63436534a4c249122302a8883ca56",
            "sentence": "I\\'d say Tom was only bluffing."
        },
        {
            "id": "20dc7f5b7757416d996b87a06074d080",
            "sentence": "I\\'m afraid I\\'ve got bad news."
        },
        {
            "id": "d42b856798554b548efdaba9c5f7a95e",
            "sentence": "I\\'m afraid I\\'ve offended you."
        },
        {
            "id": "535abb36c33646b7ababd9106234ac70",
            "sentence": "I\\'m glad that I\\'m not paying."
        },
        {
            "id": "058d99e8840a4bd08c3d6824ebebab61",
            "sentence": "I\\'ve never tried Mexican food."
        },
        {
            "id": "0c579164dace449581ed0b41c3ca1272",
            "sentence": "I\\'ve only been to Boston once."
        },
        {
            "id": "ca404eead5fd41b084c25c618e2792b3",
            "sentence": "I\\'ve read many kinds of books."
        },
        {
            "id": "c26eb26110ab4d56a48f9304236d4174",
            "sentence": "I\\'ve recently moved to Boston."
        },
        {
            "id": "f720f6f9a4394207bdda3a17a15e47ac",
            "sentence": "I\\'ve seen this picture before."
        },
        {
            "id": "b45cb223c00742f6bb56febbc07249a7",
            "sentence": "I\\'ve still got a lot to learn."
        },
        {
            "id": "0313b7d6ddc545b8a9c7e3ff4d5dc8e8",
            "sentence": "Can I have the key now, please?"
        },
        {
            "id": "93bd154da2324a72aafe0cb2564ccade",
            "sentence": "Can I have this film developed?"
        },
        {
            "id": "cb1f60995c874e3e95b6d88d25dfa220",
            "sentence": "Can I see your license, please?"
        },
        {
            "id": "e019cd4d4e1144f0894ebd1fc0c20aec",
            "sentence": "Can I talk to you for a second?"
        },
        {
            "id": "a0675ccdc03d4d1aaa09da127d7cf683",
            "sentence": "Can I use my medical insurance?"
        },
        {
            "id": "de676a080ffa4ed393ea3aaaf9792300",
            "sentence": "Can we do it on Monday instead?"
        },
        {
            "id": "b6a6169dbcee40929930f651437cde62",
            "sentence": "I think it won\\'t be a problem."
        },
        {
            "id": "bde11cebdf844fcda2512fde6d20af2c",
            "sentence": "Tom saw Mary earlier this week."
        },
        {
            "id": "b868097326724a1a9c837b2f4f758023",
            "sentence": "Tom saw Mary eating a sandwich."
        },
        {
            "id": "a99d474c89a648e79616eeeeb83fe179",
            "sentence": "Tom saw Mary reading his diary."
        },
        {
            "id": "420e741b95e44bc696f638e11821cff1",
            "sentence": "Tom saw Mary return home alone."
        },
        {
            "id": "ff0677245b4844d9b03b777e2d137a3b",
            "sentence": "I wonder why Tom is so nervous."
        },
        {
            "id": "938e5cc140e743ae88c07e7d229baef8",
            "sentence": "I wonder why Tom is so thirsty."
        },
        {
            "id": "fb6d99cff7de46378eb74c9cc8576292",
            "sentence": "I wonder why Tom is so worried."
        },
        {
            "id": "c0cde29738774252b3fc0504060742dd",
            "sentence": "I wonder why Tom was so afraid."
        },
        {
            "id": "d62de7f762044b878a666603470ca8b6",
            "sentence": "I wonder why Tom was surprised."
        },
        {
            "id": "2a70b7211d8c421a965c911cc01ba17d",
            "sentence": "I wonder why Tom was suspended."
        },
        {
            "id": "904a4cf1dbf94f5689cb79b1f50ae21f",
            "sentence": "That\\'s what Tom gets paid for."
        },
        {
            "id": "e6337ed960304494b3443cd45b73ba3e",
            "sentence": "I don\\'t really have any plans."
        },
        {
            "id": "a3e63437688f4b74a39029ad22a3c168",
            "sentence": "I don\\'t really need your help."
        },
        {
            "id": "30b514c6221b48df8bc868123aebfb95",
            "sentence": "I don\\'t really sing like that."
        },
        {
            "id": "0c00a0b5063e4d63839f80e53a9b0338",
            "sentence": "I don\\'t really think about it."
        },
        {
            "id": "1df1ccea4043484e893bec4834f84cfa",
            "sentence": "I don\\'t really understand why."
        },
        {
            "id": "cc69d7c432494c9f98b5d8acf5604c52",
            "sentence": "I don\\'t really understand you."
        },
        {
            "id": "5dcb93c85e574e2e8dbf56c0d522c670",
            "sentence": "What Tom says isn\\'t important."
        },
        {
            "id": "8dfc3064a2254af3b5603a478132c2e9",
            "sentence": "What Tom told you wasn\\'t true."
        },
        {
            "id": "8f55e85232dc423997625f2ae3ac666e",
            "sentence": "I\\'m going to Tom\\'s on Monday."
        },
        {
            "id": "c6c9b8f95b104494801437d6fb5ab4d3",
            "sentence": "I knew you\\'d get here in time."
        },
        {
            "id": "938c3726b852498da2c855756ca5866a",
            "sentence": "What\\'s Tom been doing all day?"
        },
        {
            "id": "0921d0235ba64b5a8ab7d4e4a5c62d09",
            "sentence": "What\\'s Tom going to think now?"
        },
        {
            "id": "1b929af2b69f40bf8c13b4a234912a86",
            "sentence": "What\\'s that bucket doing here?"
        },
        {
            "id": "64743166a9ca49f4a3c555730ecf3ff3",
            "sentence": "What\\'s that smell like to you?"
        },
        {
            "id": "0ced4fa640d7422f91568e2d128bf35b",
            "sentence": "What\\'s the date of the letter?"
        },
        {
            "id": "4c940b6422434835bd6c6b98353e889f",
            "sentence": "The plane is about to take off."
        },
        {
            "id": "2015bbcf4b9d45eca4d9c6edf10c3161",
            "sentence": "Tom might want to talk to Mary."
        },
        {
            "id": "5798a6205dc144a0929063fa77cbe99d",
            "sentence": "Tom moved into my neighborhood."
        },
        {
            "id": "2f1e0af28ff946faaceaccec4995d23d",
            "sentence": "Tom must be from the Australia."
        },
        {
            "id": "08ba9db031254cec8b29e978ba012ef6",
            "sentence": "Tom must conserve his strength."
        },
        {
            "id": "485eb5767cb7457abb9a48bc27d0042b",
            "sentence": "Is somebody going to let me in?"
        },
        {
            "id": "f3e6500216cb4ad19675a6995b3fe997",
            "sentence": "Is something else worrying you?"
        },
        {
            "id": "6905d82d31d8411d9e678b51d774cd56",
            "sentence": "Is that really going to happen?"
        },
        {
            "id": "bdce28eb92fb47159c9de5d570a1d59e",
            "sentence": "Is that ring made of real gold?"
        },
        {
            "id": "b2966a7f58bf42299181362a9406fd3d",
            "sentence": "Is that something you expected?"
        },
        {
            "id": "371932d4a2a142f2a501733f6ff7b492",
            "sentence": "Is that what you were thinking?"
        },
        {
            "id": "d622650c10d044408284b7523273c2f6",
            "sentence": "I don\\'t know where I was born."
        },
        {
            "id": "09958adca6f246d19aaca6923b7004fc",
            "sentence": "I don\\'t know where Tom is now."
        },
        {
            "id": "7a72f58398cc4ad6a9bb4954bed2bdb1",
            "sentence": "I don\\'t know where to turn to."
        },
        {
            "id": "5aa386fd55f64494b8a93949b3173184",
            "sentence": "I don\\'t know which key to use."
        },
        {
            "id": "3e5c1cb3a8094a4ea6b220f62c8974bb",
            "sentence": "I don\\'t know which one I want."
        },
        {
            "id": "3d921e155d5849cd8c28fe52a0c2b07a",
            "sentence": "Too many cooks spoil the broth."
        },
        {
            "id": "86673a210e6744f99b1b99aef6c9597a",
            "sentence": "Uranus and Neptune are similar."
        },
        {
            "id": "176ae749585446e485ce33ceedadb966",
            "sentence": "We are all at different levels."
        },
        {
            "id": "59f66de00ce244969994ade3de643f13",
            "sentence": "I didn\\'t say it happened here."
        },
        {
            "id": "32941f5bb5384c49bc0c860e4911bdd7",
            "sentence": "I didn\\'t see the fire hydrant."
        },
        {
            "id": "87ac7513f0f0473dbf52f797b92a23e0",
            "sentence": "I didn\\'t see your car outside."
        },
        {
            "id": "408444d0046a4947813bf72fff061a76",
            "sentence": "You\\'re lucky Tom didn\\'t come."
        },
        {
            "id": "8815e359456949fea98210540f4267bc",
            "sentence": "How do you think you\\'re doing?"
        },
        {
            "id": "8fd074141848471685e97419a22e9bc0",
            "sentence": "I hope it\\'ll be fine tomorrow."
        },
        {
            "id": "9c2f9c70652a4153a59d73e30201859c",
            "sentence": "Why would you want to buy that?"
        },
        {
            "id": "04d56488f2ee4a609b3549a09f624b86",
            "sentence": "Why would you want to help Tom?"
        },
        {
            "id": "70b17e0556a34e388415832dbc06b7e6",
            "sentence": "Why would you want to hire Tom?"
        },
        {
            "id": "b1202f832f234639bc2435b3d1f6d47f",
            "sentence": "Tom is my neighbor\\'s grandson."
        },
        {
            "id": "ece18c0028b74451b1bad0bc59598a03",
            "sentence": "Tom is my sister\\'s ex-husband."
        },
        {
            "id": "327ed6b0ac0846efaf56e441631d06de",
            "sentence": "Tom was late, but Mary wasn\\'t."
        },
        {
            "id": "272ccc8e62654facb59c94fbb3e0e553",
            "sentence": "Tom wasn\\'t with us last night."
        },
        {
            "id": "0a9738433fe84e418eeadfa2166512f2",
            "sentence": "Why would Tom want to go there?"
        },
        {
            "id": "85ac7d2ebd47424b84332c1e29e5c018",
            "sentence": "Why would they need to do that?"
        },
        {
            "id": "15ec912290f44d6f9b3d1dff8ba56183",
            "sentence": "Why would they want to do that?"
        },
        {
            "id": "4cf4120c899f4b439e49cee5f5be5e16",
            "sentence": "Why would we want you to leave?"
        },
        {
            "id": "9bf01ae5b7f64f309befe9ac64a97f6d",
            "sentence": "There was blood on Tom\\'s face."
        },
        {
            "id": "50856230dcf841628334638ce17e4573",
            "sentence": "I hope everything\\'s all right."
        },
        {
            "id": "6f429221b2814bdc963dce3c3cc87920",
            "sentence": "I hope it doesn\\'t ever happen."
        },
        {
            "id": "41fe4464d8a4465a83c89755033537b8",
            "sentence": "I hope that I don\\'t regret it."
        },
        {
            "id": "1fd0300b3fcd4c0b818a581d0771dfb4",
            "sentence": "I have the right to speak, too."
        },
        {
            "id": "342001da9f9e4433a762a58905b60318",
            "sentence": "Tom needed money from the bank."
        },
        {
            "id": "67c3773338c84e3da193aef9bcf3580a",
            "sentence": "What\\'re you doing with my car?"
        },
        {
            "id": "e619a8a6385148b4b3181e8f990183f7",
            "sentence": "I write poetry in my free time."
        },
        {
            "id": "fec39a3e0ff14b2c9e013127ded173f7",
            "sentence": "I wrote a letter to my teacher."
        },
        {
            "id": "62607ae9b7f449ccba05402372fc6f17",
            "sentence": "I wrote this song just for you."
        },
        {
            "id": "d94d471e9ae8437291037abbb12747f8",
            "sentence": "Tom and I went back to the bar."
        },
        {
            "id": "319490de248540b28f96c21cda55f924",
            "sentence": "Tom and I were laughing at you."
        },
        {
            "id": "29e53055ad21431ea1f5792d77d6144c",
            "sentence": "Tom and I were on the same bus."
        },
        {
            "id": "5c361bd7725e4f2da7da7bbb6763be33",
            "sentence": "Everything smells so delicious."
        },
        {
            "id": "22b3c8f2351e413285dd704ba28f965c",
            "sentence": "Everything was going perfectly."
        },
        {
            "id": "2cf02e0faa084052a325d6a92908baf0",
            "sentence": "Everything went horribly wrong."
        },
        {
            "id": "9891df9e6f8b4dd8a23f25f6a735675a",
            "sentence": "Exactly how much did that cost?"
        },
        {
            "id": "16a05166bd414cdcaee32fbbd3d65ef5",
            "sentence": "Tom says Mary needs to do that."
        },
        {
            "id": "312f691c91f4417fb39320d491435a64",
            "sentence": "Tom says Mary ought to do that."
        },
        {
            "id": "a88f7e2d665c46c5be586f31787f12e2",
            "sentence": "Tom says Mary seldom does that."
        },
        {
            "id": "9f51c629f46d4dccbca50fa571301b8a",
            "sentence": "Tom says Mary seldom eats fish."
        },
        {
            "id": "cce5275a73c24e1b8ee749cbdde5c50d",
            "sentence": "Tom says Mary still needs help."
        },
        {
            "id": "3375e5a3788f4641ad9711a2cd70f85b",
            "sentence": "Tom was slow, but Mary wasn\\'t."
        },
        {
            "id": "9351cd8dbce94bf08a83d4b801da2ee0",
            "sentence": "This will be extremely helpful."
        },
        {
            "id": "9a24727a60e44b18bf7d0a2c944cf4cd",
            "sentence": "Do you think that\\'s necessary?"
        },
        {
            "id": "7eeba42edf774cfd990322be6f07bc69",
            "sentence": "Do you think there\\'s a chance?"
        },
        {
            "id": "43dc4d3929654e7fb248cdd4053f33f5",
            "sentence": "Do you think they\\'ll find Tom?"
        },
        {
            "id": "743313cc38344aa9b117bab65cf2a147",
            "sentence": "Tom won\\'t leave Mary with you."
        },
        {
            "id": "3c8c7754fbf54e0cbe10e7020790acf9",
            "sentence": "Tom won\\'t let anybody do that."
        },
        {
            "id": "2c84025b240c46d5b88410ecdf1cba05",
            "sentence": "Tom won\\'t let anyone touch it."
        },
        {
            "id": "d693bb77b1a9459dae5fdc41b2cc6360",
            "sentence": "Tom won\\'t lie for you anymore."
        },
        {
            "id": "16073b6596e445838adbc593924d79e4",
            "sentence": "Tom won\\'t like our doing that."
        },
        {
            "id": "6bc5d713be324b9884c8a11940c47b5a",
            "sentence": "Tom won\\'t likely be awake now."
        },
        {
            "id": "b95d8703ff084a2f95ed1c8381ffc1dc",
            "sentence": "I haven\\'t done that this year."
        },
        {
            "id": "d0c9b3196cc249639058e8c1797bbd9f",
            "sentence": "Can you come on Sunday evening?"
        },
        {
            "id": "dfdd43c1dad04c698a8fb77befc72950",
            "sentence": "Can you deliver it to my house?"
        },
        {
            "id": "337d542b44484e9bb7aa2a0e2e1f93f2",
            "sentence": "Can you give me a better price?"
        },
        {
            "id": "47764b8091c944a9abcc24b54c57a02b",
            "sentence": "Can you give me some specifics?"
        },
        {
            "id": "78d6556808f84c87b4938dba97b14c30",
            "sentence": "Can you help me make a snowman?"
        },
        {
            "id": "b0b1e7f11b9e450e9b659cc2b1f85e91",
            "sentence": "Did you think I wouldn\\'t come?"
        },
        {
            "id": "adb15e1b78834bb2be23f563d7b1c5c0",
            "sentence": "Didn\\'t you write him a letter?"
        },
        {
            "id": "ce9a3635731648aba8f9ce16e08aafa4",
            "sentence": "Tom said Mary was going to win."
        },
        {
            "id": "1a719a5fcb22429b94026046e926a2f7",
            "sentence": "Tom said Mary was his daughter."
        },
        {
            "id": "97922abde26b4a048dac9a1f4736061f",
            "sentence": "Tom said Mary was really drunk."
        },
        {
            "id": "97471e3488394b0dac2a3f8f5485bd38",
            "sentence": "Tom says he doesn\\'t like Mary."
        },
        {
            "id": "8099c10566be4ae4a8a4b9a568f1d4ba",
            "sentence": "Tom says he won\\'t get married."
        },
        {
            "id": "5910c77854e14f55a251050fd69f0caa",
            "sentence": "I want to have a cup of coffee."
        },
        {
            "id": "edb168bc61094d5cb8224c8080b1af68",
            "sentence": "I want to personally thank you."
        },
        {
            "id": "add702c73b1a432aadf83e5856926a54",
            "sentence": "I want to say something to you."
        },
        {
            "id": "7338fba95725494fb78b52a12a2c1fe1",
            "sentence": "I want to show you my drawings."
        },
        {
            "id": "76dd8c6c16f34bb688afc5889d5c1e79",
            "sentence": "I\\'m envious of Tom\\'s success."
        },
        {
            "id": "c55c9884bc144e5d877e31e8d29bdea0",
            "sentence": "I want you to be my girlfriend."
        },
        {
            "id": "edba4681124a47b0b7cf872c2a0f5d36",
            "sentence": "I want you to leave right away."
        },
        {
            "id": "793c564962a342cc83cddaefe947928a",
            "sentence": "I\\'d like a little bit of help."
        },
        {
            "id": "4d8e1038e72345cba5c5b37e430857e2",
            "sentence": "I\\'d like to be as rich as Tom."
        },
        {
            "id": "5f0296d091a140caa65c731cb78cf4c7",
            "sentence": "I\\'d like to know your opinion."
        },
        {
            "id": "90200f700f61461db0b306f453549ee1",
            "sentence": "Are you through with your work?"
        },
        {
            "id": "12b9adc74ec7476db0eaa5dd604bd983",
            "sentence": "Are you trying to get me fired?"
        },
        {
            "id": "1c868f6609764439b51d587493006874",
            "sentence": "I have three questions for you."
        },
        {
            "id": "90f435697d8b4350a6cf4ac8e36d17c3",
            "sentence": "I don\\'t think we want to know."
        },
        {
            "id": "6db65fec03644e1e8fc855c047762aec",
            "sentence": "I don\\'t understand you at all."
        },
        {
            "id": "760cc0be4b37428f9304f4f0404a904d",
            "sentence": "I don\\'t usually eat breakfast."
        },
        {
            "id": "0b6cff6f2925486f9cae4fa8a7f31100",
            "sentence": "I don\\'t want Tom to come here."
        },
        {
            "id": "114e25ea88024c8287bec6ffc6650e73",
            "sentence": "I don\\'t want Tom to get upset."
        },
        {
            "id": "ba09f860972b42c0b37b8cd79923f72f",
            "sentence": "Don\\'t you remember doing that?"
        },
        {
            "id": "562914213e6c4b6fb7d6eab5b8e119ab",
            "sentence": "Don\\'t you remember my promise?"
        },
        {
            "id": "d9bdad5d1304459093a5bf9f0577ab6e",
            "sentence": "Don\\'t you see what that means?"
        },
        {
            "id": "eb3908e2b0cd47759527359d35943d17",
            "sentence": "Don\\'t you see what this means?"
        },
        {
            "id": "d73ffd880dc94f669c6b3e52ccbfba2d",
            "sentence": "Did you encounter any problems?"
        },
        {
            "id": "f62ab702b67d444894672a13af933e44",
            "sentence": "Do they speak French in Canada?"
        },
        {
            "id": "76639346525d4971a48a325b75372a49",
            "sentence": "Tom said he was from Australia."
        },
        {
            "id": "4285e25356b64fdcb1e9a11af031e3b0",
            "sentence": "Tom spent many years in prison."
        },
        {
            "id": "99eca3b4701248b6b50ebfbdf5d682b8",
            "sentence": "Tom threatened to kill himself."
        },
        {
            "id": "af550eb768c84208bd59e53dedacdbad",
            "sentence": "Tom tried to make Mary jealous."
        },
        {
            "id": "648084b49f0c4bf086bc917b18e2a6ba",
            "sentence": "Can you hold this for a second?"
        },
        {
            "id": "dcfb80243b5b4bc6932d28b7f557d5b7",
            "sentence": "Can you lend me a little money?"
        },
        {
            "id": "97b8554bdcff4456a7700d9a4a6d8e2b",
            "sentence": "Can you see that Tom gets home?"
        },
        {
            "id": "bc11bff8c587461bb1c289ffed695d77",
            "sentence": "Can you show me the way please?"
        },
        {
            "id": "872d45cfeea44be3b3464a47ebe944c8",
            "sentence": "Can you show me those pictures?"
        },
        {
            "id": "8836aac612af4528a8db20d4952431f4",
            "sentence": "Can you tell me about yourself?"
        },
        {
            "id": "dbdf9d9a99574f70b1ef328aa17c4c3e",
            "sentence": "My phone needs to be recharged."
        },
        {
            "id": "845d759064a04b1383a85009a786b2fb",
            "sentence": "My wife wants to adopt a child."
        },
        {
            "id": "ba33fbfa30f74134997d316dbf763958",
            "sentence": "Neither Tom nor Mary had a job."
        },
        {
            "id": "480f4cf2b5e6471f932f659e50636567",
            "sentence": "No injuries have been reported."
        },
        {
            "id": "ad937227318844bc8e99c11dfb0ac77d",
            "sentence": "No one could solve the problem."
        },
        {
            "id": "9bc37f8081774cd599ac87ddf6d8ac88",
            "sentence": "Tom inspired us to work harder."
        },
        {
            "id": "af6dde7de0714fedb109cc0fa0bd46f2",
            "sentence": "Tom is a pleasure to work with."
        }
    ],
    "nbPages": 3576,
    "nbResults": 715026
}