{
    "currentPage": 2925,
    "pageSize": 200,
    "items": [
        {
            "id": "81379861d7414783b38c66356543da04",
            "sentence": "Don\\'t walk away when I\\'m talking to you."
        },
        {
            "id": "4564b6c36c9c49a6a4032c4a392f1606",
            "sentence": "Don\\'t you think that you\\'ve done enough?"
        },
        {
            "id": "cce659e4409c450e8af1ea05e60d7f9a",
            "sentence": "Don\\'t you think that\\'s a little strange?"
        },
        {
            "id": "d4225153958645feacc7bff7892f0de2",
            "sentence": "You look like a little girl in that dress."
        },
        {
            "id": "34562369f563451db8679a1584ac1d37",
            "sentence": "You should have left half an hour earlier."
        },
        {
            "id": "c2ad716c10dc4a54bf963dee891a824d",
            "sentence": "Tom removed the bandages from Mary\\'s leg."
        },
        {
            "id": "ecc0fdbe749a43c28976de98a2c95143",
            "sentence": "Tom said he won\\'t be in Boston next week."
        },
        {
            "id": "602dd5bccd7b44a082c4cc59fa3ececc",
            "sentence": "Why don\\'t we eat at a restaurant tonight?"
        },
        {
            "id": "9c257380934248aca7f78f515321b4d6",
            "sentence": "Why don\\'t we talk about this over dinner?"
        },
        {
            "id": "fd203c3f49e343c597590c9cb0fd2621",
            "sentence": "Why don\\'t you stop by for a little while?"
        },
        {
            "id": "da866fb0d0a3407aaed66fbae7548aed",
            "sentence": "Tom never really wanted to live in Boston."
        },
        {
            "id": "c480db9151504e7fa68ddeaeb7ab783c",
            "sentence": "Tom noticed that the garage door was open."
        },
        {
            "id": "c221b6ea17a745a08d35f8b3011683b6",
            "sentence": "Tom now drinks a lot more than he used to."
        },
        {
            "id": "d88df73448104fc79263ac2d218ec9be",
            "sentence": "Tom often borrowed money from his friends."
        },
        {
            "id": "1ae5013ee02a495b8cd96be2276f8edf",
            "sentence": "Tom only has three hours to get that done."
        },
        {
            "id": "e73e0b6587ae49218e7135670181cfe6",
            "sentence": "Tom is the most influential man in Boston."
        },
        {
            "id": "0bd278eb47474acc917396c13718bd57",
            "sentence": "Tom is the one who showed me how to do it."
        },
        {
            "id": "ae383d5138fd404b946d39a0b1bb2aa8",
            "sentence": "Tom is the one who told me where you live."
        },
        {
            "id": "c806a40f6b0f4a678c92d61c65c473ee",
            "sentence": "Tom is the only breadwinner in the family."
        },
        {
            "id": "ec893f21554346b9abaf53f658f20c48",
            "sentence": "Tom is the only one here that can do this."
        },
        {
            "id": "cf9dfeea7d544a07855593d3422af42e",
            "sentence": "Tom is the only one who saw what happened."
        },
        {
            "id": "131cf571d205497aa18e8d53edde5d47",
            "sentence": "Make sure you tell Tom to be here by 2:30."
        },
        {
            "id": "127f3db4f04248308f28c3f397ba194f",
            "sentence": "Tom and Mary said they weren\\'t Canadians."
        },
        {
            "id": "297dc941a1b746d482b8be6bf580c026",
            "sentence": "Tom and his wife don\\'t have any children."
        },
        {
            "id": "13334b741946481eae1b627ad4ccb31c",
            "sentence": "Young children have short attention spans."
        },
        {
            "id": "9e69384141114d14a746015b0c7c9315",
            "sentence": "Your children are remarkably well-behaved."
        },
        {
            "id": "8267f98afdec485cb453315129fea1cb",
            "sentence": "Your hypothesis is completely unrealistic."
        },
        {
            "id": "8896da7cea62466dbedd9e4927625656",
            "sentence": "My mother told me I have to behave myself."
        },
        {
            "id": "ec11ef5e52e84b54b21d0861b1d2517e",
            "sentence": "My personal life is none of your business."
        },
        {
            "id": "a459a6b3d110424ca4f14d146de9fbfc",
            "sentence": "My plan for the summer is to go to Europe."
        },
        {
            "id": "ac19c55cd37b49c186f80a2780badacf",
            "sentence": "My son thinks women are stronger than men."
        },
        {
            "id": "d52ace44d35a4993b66d5676453043d2",
            "sentence": "My trip to Australia is officially booked."
        },
        {
            "id": "145e76f0e6174e42834206ef9a4be2c5",
            "sentence": "My uncle has lived in Paris for ten years."
        },
        {
            "id": "c39dee381b0f43f593cc25db2fbc302c",
            "sentence": "I don\\'t believe this is really happening."
        },
        {
            "id": "3b022e16131e4052ad251a6af04dd1cc",
            "sentence": "Tom doesn\\'t watch TV except on Saturdays."
        },
        {
            "id": "b18ee04436464b0da7c4ad98828ce511",
            "sentence": "Tom knew something went wrong, didn\\'t he?"
        },
        {
            "id": "3f951322798c4541845a7472ddd7e0c4",
            "sentence": "Tom told me that he hadn\\'t done that yet."
        },
        {
            "id": "742827961c3842d0b455cb15aca14b0a",
            "sentence": "My boss has never invited me to her house."
        },
        {
            "id": "8b5d36f049f54090b8f78d1dcafaf239",
            "sentence": "My father has been out of work for a year."
        },
        {
            "id": "08bdf67a35e847f9b77751410bd684b3",
            "sentence": "My father has never been sick in his life."
        },
        {
            "id": "59bfd3c19f5649d5995b2dac3ad083f3",
            "sentence": "My father is going to go abroad next week."
        },
        {
            "id": "5b1c41c9eab84bf3a99977c986fb3875",
            "sentence": "My father used to read me bedtime stories."
        },
        {
            "id": "bd974bf0a10d4a289f629a75836f7cdc",
            "sentence": "My grandfather gave me a birthday present."
        },
        {
            "id": "f7403424007b41cb81c20c9212425e63",
            "sentence": "My guess is that it will be fine tomorrow."
        },
        {
            "id": "872e718551d24e78befaaca8a208e586",
            "sentence": "What Tom ate for dinner didn\\'t cost much."
        },
        {
            "id": "22492eae4fbf4a54bf7ecc1b2975eed1",
            "sentence": "Unfortunately, there may be complications."
        },
        {
            "id": "cd933e6870c640a5a3a37e075492b621",
            "sentence": "We are giving Tom a party on his birthday."
        },
        {
            "id": "518c76dff80f489491f824053c8c36ed",
            "sentence": "We can hear the church bell every morning."
        },
        {
            "id": "569cbacc128b40e490f90f6cf7a1445f",
            "sentence": "Tom doesn\\'t know what\\'s really going on."
        },
        {
            "id": "4570a1fc5ee44116a57a3df269958ec7",
            "sentence": "Didn\\'t you know Tom used to study French?"
        },
        {
            "id": "110f991979614e84a6ae4adf8158afb0",
            "sentence": "Didn\\'t you know Tom was going to do that?"
        },
        {
            "id": "e2b0594c244840bc848ed5594d4b752e",
            "sentence": "Didn\\'t you know that Tom was dating Mary?"
        },
        {
            "id": "074236acb2924e62adf7a16f6a07a308",
            "sentence": "Tom says he could never live in Australia."
        },
        {
            "id": "906addd71c374090b90d2f20dfb30616",
            "sentence": "Tom may not have done what he said he did."
        },
        {
            "id": "4d76c32c733142b085b452821b9ff1b1",
            "sentence": "Tom mentioned he had to work next weekend."
        },
        {
            "id": "0e97a5d138cb46ba81435ea9ce7856c0",
            "sentence": "Tom might be able to do something to help."
        },
        {
            "id": "57b8553e27e34b8dbb05e01b5cf39e37",
            "sentence": "Tom might be able to get your car running."
        },
        {
            "id": "69760c6a2620473a9ebda9201ea24811",
            "sentence": "I suppose you already know that\\'s my car."
        },
        {
            "id": "973283be886b487f9f8043bd220b918f",
            "sentence": "I suppose you\\'ve already bought a ticket."
        },
        {
            "id": "f5861d1c018849b2b625bbcf6f582e2b",
            "sentence": "I think I\\'ll start with a bottle of beer."
        },
        {
            "id": "f9b0010b35f949668abdb2284fdfc524",
            "sentence": "I\\'ve already told Tom what he should buy."
        },
        {
            "id": "647b559b6a004bceab025b347fa578e7",
            "sentence": "I\\'ve always wanted to try riding a horse."
        },
        {
            "id": "d1efafa2d211410c9d1eadfd9239acdc",
            "sentence": "I\\'ve decided to stay for a few more days."
        },
        {
            "id": "ade5cf2d2c604563a8f40674997d0114",
            "sentence": "Tom says he sees things that I can\\'t see."
        },
        {
            "id": "1327c4d3793a40fcb6d7aedd99e6b35e",
            "sentence": "Tom says he\\'s read this book three times."
        },
        {
            "id": "4a5bf8cad1794eb9b3688f2aea30d6a4",
            "sentence": "Tom took home Mary\\'s umbrella by mistake."
        },
        {
            "id": "f5c08dbeab354887bc11ad226addac0d",
            "sentence": "Tom wasn\\'t the one who started the fight."
        },
        {
            "id": "e1c4469335d24ca8af05c7b44aebbd51",
            "sentence": "Tom knows that not everyone here can swim."
        },
        {
            "id": "3fa2f7c49b21489b8de1bc6b934e2707",
            "sentence": "Tom left the waitress a thirty dollar tip."
        },
        {
            "id": "a309211aa3774fba9659b28a59ee7c50",
            "sentence": "Tom lets Mary do whatever she wants to do."
        },
        {
            "id": "54274dd8fa2c4b408bb37eacb1e52310",
            "sentence": "Tom lives in Boston with his grandparents."
        },
        {
            "id": "6af0f16e53fe4d21b9e099c954589169",
            "sentence": "Tom makes the best spaghetti in the world."
        },
        {
            "id": "0911a85a79e74d69b66fcc6f7385599c",
            "sentence": "You\\'re still a fire fighter, aren\\'t you?"
        },
        {
            "id": "e575d202d2ae4c9183ab4c0960c80123",
            "sentence": "You\\'re the only one who\\'s talked to Tom."
        },
        {
            "id": "214b5f408544406f8d1bb12aaeb101ca",
            "sentence": "He doesn\\'t eat anything other than fruit."
        },
        {
            "id": "a363d1bf2ab64588822fea4bd902620c",
            "sentence": "There\\'s no question about Tom\\'s loyalty."
        },
        {
            "id": "8944fbe8fcb34ab1985099f6e63b65c8",
            "sentence": "There\\'s nothing I can do that Tom can\\'t."
        },
        {
            "id": "e43d3d0817594e6da6ec01bcdb972503",
            "sentence": "Tom accused me of having stolen his watch."
        },
        {
            "id": "5ad790005be0490f81f657a2528dd95a",
            "sentence": "Tom admitted that what Mary said was true."
        },
        {
            "id": "820fb7dce55447e6a49755ae36e300c2",
            "sentence": "Tom almost never complains about anything."
        },
        {
            "id": "b58fd754241943cfa4725cc3248d5435",
            "sentence": "Tom always complains about what Mary does."
        },
        {
            "id": "a2652c116fb6405eb3dde148a727fdde",
            "sentence": "Tom and I have no secrets from each other."
        },
        {
            "id": "29de5e7bd61b48c7a5f861b4d20a4b00",
            "sentence": "Tom and Mary are trying to calm John down."
        },
        {
            "id": "a875123706684036a64f2f577f9f640f",
            "sentence": "You\\'ll never forget it, I\\'m pretty sure."
        },
        {
            "id": "486f973e7ba14014b753e2058e50c59c",
            "sentence": "Tom was lying unconscious on the sidewalk."
        },
        {
            "id": "d5af9eadc9934016b598730e90c36dcc",
            "sentence": "Tom was mauled by a dog when he was a kid."
        },
        {
            "id": "da71f2678a4049f9a6e2c25e2dfbccae",
            "sentence": "Tom was much stronger when he was younger."
        },
        {
            "id": "4819f6bf91cd464bbee8874abf77b556",
            "sentence": "Tom was never the same after his accident."
        },
        {
            "id": "87c9cde987a8465998dba082082792e9",
            "sentence": "Is this the key your uncle is looking for?"
        },
        {
            "id": "f2a65cd6f53a45e6902738a3f1f39a9d",
            "sentence": "It cost me 5,000 yen to repair my bicycle."
        },
        {
            "id": "acc5aac14f924b778c695e9be7eb70c0",
            "sentence": "A lot of kids don\\'t wear bicycle helmets."
        },
        {
            "id": "5b8c573f148f4dfbb3379648e67100d6",
            "sentence": "Tom waited three hours and then went home."
        },
        {
            "id": "1885be3cf89749419e273dba129fd036",
            "sentence": "Tom walked over to the door and opened it."
        },
        {
            "id": "2e28da0999a64b6b9903db44d21fb799",
            "sentence": "I don\\'t think Tom knows anyone in Boston."
        },
        {
            "id": "a85af88e488b43c987074bac5e8c7e81",
            "sentence": "I don\\'t think Tom knows that I love Mary."
        },
        {
            "id": "b8b340d494c84795ac379e7800b43c70",
            "sentence": "I don\\'t think Tom should go there by car."
        },
        {
            "id": "ac330db30b284adea37b029ea35153e9",
            "sentence": "I don\\'t think Tom would enjoy doing that."
        },
        {
            "id": "e4d415a8a5c044da80c42ebfd59955a4",
            "sentence": "I don\\'t think Tom would like living here."
        },
        {
            "id": "189cca67021c429fb6e77088fdab8d89",
            "sentence": "You should\\'ve seen that movie last night."
        },
        {
            "id": "a943f53275c54da2ba0adbb6c1298817",
            "sentence": "You shouldn\\'t be impatient with children."
        },
        {
            "id": "f57b04e2d87f4fa3bfa1627b0f84ece8",
            "sentence": "You shouldn\\'t visit my grandfather today."
        },
        {
            "id": "6aca64fc9b9b4c6682e42732d05e9c5f",
            "sentence": "Tom and Mary eat lunch together every day."
        },
        {
            "id": "736e06b42a824c1b9f233f8a6c8d6154",
            "sentence": "Tom and Mary fell in love with each other."
        },
        {
            "id": "2292e80180384710a53d4072d8f3703f",
            "sentence": "Tom and Mary got married on Christmas Eve."
        },
        {
            "id": "0b1d302dcd6f4f2ea334379e3a998717",
            "sentence": "Tom and Mary have a platonic relationship."
        },
        {
            "id": "532300fec10549a69505d2e6a6dac86f",
            "sentence": "Tom and Mary have already left for Boston."
        },
        {
            "id": "c9ec4620be8141a38dc44a33c49e63f6",
            "sentence": "Tom and Mary have postponed their wedding."
        },
        {
            "id": "85507ea3b95f45289fbc4d18098b22d5",
            "sentence": "Tom wasn\\'t able to contact Mary by phone."
        },
        {
            "id": "546516c3bac944e3a4568ea027984a27",
            "sentence": "I can stay with Tom for a couple of weeks."
        },
        {
            "id": "a40ebe58268f473fa1984bfdeb43eb1e",
            "sentence": "I can try to keep Tom from hurting anyone."
        },
        {
            "id": "cdcbc3fc67c54aafa8194cf7a98a304b",
            "sentence": "Tom told Mary he\\'d stay at John\\'s place."
        },
        {
            "id": "6ae94c08cf85419e930abbce68afb340",
            "sentence": "Tom shouldn\\'t tell Mary to go home early."
        },
        {
            "id": "a0d0095f7bb347bc80e4c7d97916ef34",
            "sentence": "Tom showed up at John and Mary\\'s wedding."
        },
        {
            "id": "bb62dee5690d4e7985f5d608af94bdba",
            "sentence": "I don\\'t understand why that\\'s important."
        },
        {
            "id": "2f013b4be40d45639b6393d8919634b4",
            "sentence": "Tom never really wanted to sell his house."
        },
        {
            "id": "826962bc83a74d8dbf10e30916fcb23e",
            "sentence": "Tom never said what he was planning to do."
        },
        {
            "id": "78be5c71a83848ea8b9e4f4758120e6d",
            "sentence": "Tom never said who he was with last night."
        },
        {
            "id": "42fd28268be042c38beae8e9173edf46",
            "sentence": "Tom never should have eaten those oysters."
        },
        {
            "id": "772a10d9362b4a959dc8658151082c3c",
            "sentence": "Tom never thought that Mary would say yes."
        },
        {
            "id": "b67f3bbf41cd4dd7a1f8e84486edbf5f",
            "sentence": "When you\\'re a father, you\\'ll understand."
        },
        {
            "id": "e68257f819b64d6890d87ecd9c618d06",
            "sentence": "Do you usually eat breakfast before seven?"
        },
        {
            "id": "ee1a5da34bc240a4b9634cf954e6a2fc",
            "sentence": "I didn\\'t know Tom couldn\\'t speak French."
        },
        {
            "id": "3bd4d8fd84dd4fefbca70b542e92231d",
            "sentence": "Can you believe this is already happening?"
        },
        {
            "id": "2f78256f3a63488fbda09e56d221f683",
            "sentence": "Can you recommend a good dictionary to me?"
        },
        {
            "id": "b122dfbeb7b94e3dbbb91a05c26c5a48",
            "sentence": "Can you still remember where we first met?"
        },
        {
            "id": "6a30215a4a574736bb5abbbd06f435a4",
            "sentence": "Tom couldn\\'t answer all of the questions."
        },
        {
            "id": "ab3cdc51c0264cfa9324ab1c7742993a",
            "sentence": "That chicken hasn\\'t laid any eggs lately."
        },
        {
            "id": "4dba4b6cd3e9427390c443da2b8ff827",
            "sentence": "That isn\\'t really going to happen, is it?"
        },
        {
            "id": "a48df80389ea4d7b8ff1d896841551c1",
            "sentence": "That knife came in very handy, didn\\'t it?"
        },
        {
            "id": "a2db80c74916457e8b76ca30ed8671f0",
            "sentence": "I want to thank you for what you\\'ve done."
        },
        {
            "id": "346b27d3a13f4286815af0b94df136ef",
            "sentence": "I found Tom\\'s car abandoned in the woods."
        },
        {
            "id": "e1a7f441c5984346af27073a7996879e",
            "sentence": "I have a boss who\\'s much younger than me."
        },
        {
            "id": "7c25f32d65a34f81ad7c8867c91eba4a",
            "sentence": "I have no idea what you\\'re talking about."
        },
        {
            "id": "c628672c1f104710ba21657840f27ca8",
            "sentence": "I can\\'t make myself understood in German."
        },
        {
            "id": "e085e576286c4fc897f8832e4d263f52",
            "sentence": "I can\\'t put up with the noise any longer."
        },
        {
            "id": "d3f58c7889bd4e20a278182faf16ff5e",
            "sentence": "I can\\'t remember anything else about Tom."
        },
        {
            "id": "7e50c9ee850e4fdb878c582215eac434",
            "sentence": "I can\\'t remember ever meeting you before."
        },
        {
            "id": "3d8362752d9741679e569ad16231603d",
            "sentence": "I can\\'t remember exactly where Tom lives."
        },
        {
            "id": "b8c9266055f14339a5f87cd4ebc78ab0",
            "sentence": "I can\\'t remember how to use this machine."
        },
        {
            "id": "fe69d2091a9f43c1ab01ae59ba317a41",
            "sentence": "Tom\\'s wife doesn\\'t know Mary\\'s husband."
        },
        {
            "id": "57fc7fbfee5e41e0818325ceb449500b",
            "sentence": "Tom wants to hear both sides of the story."
        },
        {
            "id": "d5f56ea467d143249b531e0de47a76af",
            "sentence": "Tom wants to keep things the way they are."
        },
        {
            "id": "9d441c084cc94b7ca48456af2620b0ba",
            "sentence": "Tom wants to learn how to play the guitar."
        },
        {
            "id": "6b7df06fa8034b87b9979903946f1739",
            "sentence": "I didn\\'t realize Tom was in the hospital."
        },
        {
            "id": "f3201cc809f345d3a14b8140ed072b31",
            "sentence": "I didn\\'t realize Tom was married to Mary."
        },
        {
            "id": "38ea1bd4f4584b5a8619635ad0a3ccc5",
            "sentence": "I didn\\'t realize that Tom had to do that."
        },
        {
            "id": "c86b018823fa4c0189ac14990438bec5",
            "sentence": "I didn\\'t realize that Tom should do that."
        },
        {
            "id": "0996fe9c18294b6198ea9be6a38738aa",
            "sentence": "I didn\\'t receive your letter until today."
        },
        {
            "id": "8b17f185e802480995a54720efd6bf2b",
            "sentence": "We must deal with this problem right away."
        },
        {
            "id": "3401aafd8243407285ce051f1dafeace",
            "sentence": "We need to check this report for accuracy."
        },
        {
            "id": "b8ce4dd3038647239a915d24b062eac9",
            "sentence": "We often express our emotions nonverbally."
        },
        {
            "id": "37e30d2fd70b4195ba328e82e3fafaab",
            "sentence": "Tom went to get a glass of water for Mary."
        },
        {
            "id": "82cdaa7c4dff45ae9890e0f446a9d244",
            "sentence": "Tom will be a hundred years old next year."
        },
        {
            "id": "7665522678bd4da98bfe577ec4636fac",
            "sentence": "Tom will have a difficult time doing that."
        },
        {
            "id": "30898ba564ac4b1da56236a49fd996df",
            "sentence": "Tom will probably know what we need to do."
        },
        {
            "id": "cde864b4a27b4b0db213898653562d3d",
            "sentence": "Tom wished Mary would tell him what to do."
        },
        {
            "id": "46bf4e15208a410c94b5402f76c845ef",
            "sentence": "I thought you might be interested in this."
        },
        {
            "id": "4a5e4add4a3a412c84a94435c76f8767",
            "sentence": "Tom found the key he had been looking for."
        },
        {
            "id": "d60b557e4c1c4d9aa486de5ab4c797c2",
            "sentence": "Tom found the keys he thought he had lost."
        },
        {
            "id": "257e5f4d451a473d838ba5a3a8a5a47c",
            "sentence": "Tom gave Mary a French-English dictionary."
        },
        {
            "id": "f16b481fe6ff4dd29807bbf9a830a1e8",
            "sentence": "Tom gave Mary permission to drive his car."
        },
        {
            "id": "ac57c6827f064ff2bed9cf2e345f6839",
            "sentence": "Tom got on the bus with his three sisters."
        },
        {
            "id": "3570f7855b1540a68b7ecf86f77c3eae",
            "sentence": "Tom says he doesn\\'t remember that at all."
        },
        {
            "id": "42c4941eb424411ea7a87f42ee6654da",
            "sentence": "Tom says he doesn\\'t think Mary does that."
        },
        {
            "id": "d6e22a90c34645bd9f6084775abff0b1",
            "sentence": "Tom says he doesn\\'t want to study French."
        },
        {
            "id": "02c32e448a7c4cbf802d52ecd7358b36",
            "sentence": "Tom says he doesn\\'t want to work outside."
        },
        {
            "id": "0bae693a858e4b50b1a662e0d382749d",
            "sentence": "Tom wasn\\'t able to read in the dim light."
        },
        {
            "id": "aca478fa0f0e433e8f5059695800b896",
            "sentence": "Tom wasn\\'t surprised that Mary was there."
        },
        {
            "id": "c832b85904fa48fab65c19bcaa347259",
            "sentence": "Tom and I are now discussing that problem."
        },
        {
            "id": "b95752668b214315a8f4895d395b7cad",
            "sentence": "Tom and I drank a bottle of wine together."
        },
        {
            "id": "371e332e85ac4c95b37eb28a997e937c",
            "sentence": "Tom and I ended up becoming close friends."
        },
        {
            "id": "a0a4ab66009e4708bf93c61273a7d99a",
            "sentence": "Tom and I looked at each other and smiled."
        },
        {
            "id": "13b0b321e3a74bc883d5865a98bd5d23",
            "sentence": "Tom might know why Mary isn\\'t here today."
        },
        {
            "id": "0770138ac34f44b89697dd24a214e953",
            "sentence": "Tom never said where he\\'d first met Mary."
        },
        {
            "id": "453f45ae4ecb4d84ad4c4926141487c7",
            "sentence": "He was covered with mud from head to foot."
        },
        {
            "id": "79fa6a6d4f6b44038e594e6d02a04999",
            "sentence": "How can you say that with a straight face?"
        },
        {
            "id": "c07bb285c6d7438c9635537e965251ce",
            "sentence": "How do you suggest I write up this report?"
        },
        {
            "id": "652515dba53543b3851cd4ceb929969f",
            "sentence": "How do you suggest we settle this problem?"
        },
        {
            "id": "0a2727009ccc4c8b9676be7b472eb553",
            "sentence": "How long does it take to get to the beach?"
        },
        {
            "id": "2401caed61134751a0da0c964786947e",
            "sentence": "Why did you buy that expensive dictionary?"
        },
        {
            "id": "a998fa30c9174379a24ccffd7028bdc3",
            "sentence": "Why did you buy this expensive dictionary?"
        },
        {
            "id": "c3d47a509ef5448496e6353649274b6a",
            "sentence": "Why did you do something stupid like that?"
        },
        {
            "id": "907ec7892f7746aa81ca8514664f56e5",
            "sentence": "I can\\'t lift as much weight as I used to."
        },
        {
            "id": "6ee76bf63a7342fd9ffbca5811896095",
            "sentence": "I can\\'t lift boxes over thirty kilograms."
        },
        {
            "id": "c20432be1ae04250b04e967cfe589e3a",
            "sentence": "I can\\'t remember the melody of that song."
        },
        {
            "id": "1125b2a22d1244bf820ea2a4a83e0106",
            "sentence": "I can\\'t remember the melody to that song."
        },
        {
            "id": "5afe49b1c8e446f7b5c72ac8c3f6679f",
            "sentence": "It won\\'t be necessary to do that anymore."
        },
        {
            "id": "422bd1a651734592b3d72dbc04b0ed22",
            "sentence": "It won\\'t be so difficult to convince Tom."
        },
        {
            "id": "374bb7f78b4e47dfb673ee88b45cbc14",
            "sentence": "It would be better if Tom didn\\'t do that."
        },
        {
            "id": "a6507de2e75c45f8924a2ecd38e9c39a",
            "sentence": "It\\'ll be easy to find someone to do that."
        },
        {
            "id": "5ec198bab6a54a37829a342e5a81e598",
            "sentence": "I apologize for not writing to you before."
        },
        {
            "id": "3f69c1bb28be4b32a230880d71381c62",
            "sentence": "I arrived at the station ten minutes late."
        },
        {
            "id": "6e5cee52251e4bb38a999b15d478e17b",
            "sentence": "I asked Tom why he wasn\\'t here yesterday."
        },
        {
            "id": "6259a0984b1140fca09757e39bc2cd9c",
            "sentence": "I assume you\\'re willing to take the risk."
        },
        {
            "id": "df2f038651ba4c48b616057c001d03e8",
            "sentence": "Tom didn\\'t want to jump across the ditch."
        },
        {
            "id": "393920cb3da7498cbe6ad78abc67b28c",
            "sentence": "Tom doesn\\'t need to wear glasses anymore."
        },
        {
            "id": "c0e2e7313683404da9d28488eaea1b47",
            "sentence": "What\\'s your favorite drink in the summer?"
        },
        {
            "id": "48e0b1edb64349d2a2273adc2c6a7ada",
            "sentence": "What\\'s your favorite part of the chicken?"
        },
        {
            "id": "f9b0d225f68346f497109ec251784108",
            "sentence": "What\\'s your problem with straight people?"
        },
        {
            "id": "5a73e2015b0a493391956f833c14ed81",
            "sentence": "What\\'s the highest mountain in the world?"
        }
    ],
    "nbPages": 3576,
    "nbResults": 715026
}