{
    "currentPage": 64692,
    "pageSize": 10,
    "items": [
        {
            "id": "315c62acab9d4f4c83e175d1e295e5d9",
            "sentence": "I\\'m pretty sure that Tom doesn\\'t know French."
        },
        {
            "id": "4415f47ff3d34c4db76704a164bfbd12",
            "sentence": "Tom was eating his dessert when the phone rang."
        },
        {
            "id": "26f7544760454e188722ca3ac61ba824",
            "sentence": "Tom was in Boston last week on a business trip."
        },
        {
            "id": "b244ecf1b7a4471e8b7f157ea61c4bcc",
            "sentence": "Tom was snuggled up in an armchair watching TV."
        },
        {
            "id": "dac2a79f31304970b696efecd6b1701d",
            "sentence": "Tom stretched out on the couch and fell asleep."
        },
        {
            "id": "180a5aecdba04fec96ec2499e81a3333",
            "sentence": "Tom stretched out on the floor and fell asleep."
        },
        {
            "id": "19f070e04c75466e80f7f76911002055",
            "sentence": "Tom stretched out on the grass and fell asleep."
        },
        {
            "id": "55e78f9cca6c453e9bbb17e091832be2",
            "sentence": "Tom struggled to walk again after the accident."
        },
        {
            "id": "8ef7ee5536914f7e9bf38dc7d7cfb6dc",
            "sentence": "Maybe Tom just didn\\'t want to talk about Mary."
        },
        {
            "id": "c4008c4b7a83414f998996de29b94341",
            "sentence": "Maybe it\\'s time for you to get a new computer."
        }
    ],
    "nbPages": 71503,
    "nbResults": 715026
}