{
    "currentPage": 65450,
    "pageSize": 10,
    "items": [
        {
            "id": "48fd89235b45414a89cedc33db787627",
            "sentence": "I\\'m glad I didn\\'t eat the cake that Tom baked."
        },
        {
            "id": "ea9617363abd413cb109c4c00577c018",
            "sentence": "I\\'m not sure that that\\'s what Tom wants to do."
        },
        {
            "id": "bcf2b2ebc8774527a06a16f878bb621b",
            "sentence": "Tom, if you\\'re not going I\\'m not going either."
        },
        {
            "id": "7dd8445b7807454f8f31c76b65ed42a7",
            "sentence": "I have no idea what we\\'re supposed to be doing."
        },
        {
            "id": "43c0bc483bd249acbff7390489ab8be8",
            "sentence": "I thought Tom would give Mary your phone number."
        },
        {
            "id": "735886876d6643deacc7deecb178152f",
            "sentence": "I thought about telling Tom about what happened."
        },
        {
            "id": "62e2bba3444d4e44b9bbe467cf378db1",
            "sentence": "I thought that Tom was going to like doing that."
        },
        {
            "id": "c109dc74744e43458229ba85c72d00ba",
            "sentence": "Tom caused a commotion at the dinner last night."
        },
        {
            "id": "fcfe55bb61b74f14999dbf45e65fedbe",
            "sentence": "Be sure to complete the work before you go home."
        },
        {
            "id": "fe560116b636456b9b4d5f790a6ae3ab",
            "sentence": "Everybody was surprised when I entered the room."
        }
    ],
    "nbPages": 71503,
    "nbResults": 715026
}